.svnignore
__init__.py
context.py
fuse.py
fuse24.py
fuse3.py
fusell.py
loopback.py
memory.py
memory3.py
memoryll.py
setup.py
sftp.py
fusepy.egg-info/PKG-INFO
fusepy.egg-info/SOURCES.txt
fusepy.egg-info/dependency_links.txt
fusepy.egg-info/top_level.txt