Metadata-Version: 1.0
Name: fusepy
Version: 1.1
Summary: Simple ctypes bindings for FUSE
Home-page: http://code.google.com/p/fusepy/
Author: Giorgos Verigakis
Author-email: verigak@gmail.com
License: ISC
Platform: UNKNOWN
